racing_telemetry/__init__.py
racing_telemetry/telemetry.py
racing_telemetry/adapter/__init__.py
racing_telemetry/adapter/adapter.py
racing_telemetry/adapter/csv_adapter.py
racing_telemetry/adapter/pandas_adapter.py
racing_telemetry/adapter/transparent_adapter.py
racing_telemetry/analysis/__init__.py
racing_telemetry/analysis/basic_stats.py
racing_telemetry/analysis/streaming.py
racing_telemetry/plot/__init__.py
racing_telemetry/plot/plots.py
racing_telemetry/retrieval/__init__.py
racing_telemetry/retrieval/graphql_retrieval_strategy.py
racing_telemetry/retrieval/influx_retrieval_strategy.py
racing_telemetry/retrieval/models.py
racing_telemetry/retrieval/postgres_retrieval_strategy.py
racing_telemetry/retrieval/retrieval_strategy.py
racing_telemetry/utility/__init__.py
racing_telemetry/utility/utilities.py
racing_telemetry-0.1.6.dist-info/LICENSE
racing_telemetry-0.1.6.dist-info/METADATA
racing_telemetry-0.1.6.dist-info/WHEEL
racing_telemetry-0.1.6.dist-info/top_level.txt
racing_telemetry-0.1.6.dist-info/RECORD
