Metadata-Version: 2.1
Name: racing-telemetry
Version: 0.1.6
Summary: A library for telemetry data analysis
Home-page: https://github.com/b4mad/racing-telemetry
Author: Marcel Hild
Author-email: hild@b4mad.net
Classifier: Programming Language :: Python :: 3
Classifier: License :: OSI Approved :: GNU General Public License v3 (GPLv3)
Classifier: Operating System :: OS Independent
Requires-Python: >=3.6
License-File: LICENSE
Requires-Dist: gql
Requires-Dist: requests
Requires-Dist: influxdb-client
Requires-Dist: pandas
Requires-Dist: requests-toolbelt
Requires-Dist: psycopg2-binary
Requires-Dist: sqlalchemy
